ai/backend/meta/__init__.py
backend.ai-22.3.0.dist-info/LICENSE
backend.ai-22.3.0.dist-info/METADATA
backend.ai-22.3.0.dist-info/WHEEL
backend.ai-22.3.0.dist-info/top_level.txt
backend.ai-22.3.0.dist-info/RECORD
