Metadata-Version: 2.1
Name: backend.ai
Version: 22.3.0
Summary: Lablup Backend.AI Meta-package
Home-page: https://backend.ai
Author: Lablup Inc.
Author-email: devops@lablup.com
License: LGPLv3
Project-URL: Documentation, https://docs.backend.ai
Project-URL: Source, https://github.com/lablup/backend.ai
Project-URL: Tracker, https://github.com/lablup/backend.ai/issues
Platform: UNKNOWN
Classifier: Development Status :: 5 - Production/Stable
Classifier: License :: OSI Approved :: GNU Lesser General Public License v3 or later (LGPLv3+)
Classifier: Intended Audience :: Developers
Classifier: Intended Audience :: Science/Research
Classifier: Intended Audience :: Information Technology
Classifier: Intended Audience :: System Administrators
Classifier: Intended Audience :: Healthcare Industry
Classifier: Intended Audience :: Financial and Insurance Industry
Classifier: Programming Language :: Python
Classifier: Programming Language :: Python :: 3
Classifier: Programming Language :: Python :: 3 :: Only
Classifier: Programming Language :: Python :: 3.9
Classifier: Operating System :: POSIX
Classifier: Operating System :: MacOS :: MacOS X
Classifier: Environment :: Console
Classifier: Environment :: No Input/Output (Daemon)
Classifier: Topic :: Scientific/Engineering
Classifier: Topic :: Scientific/Engineering :: Artificial Intelligence
Classifier: Topic :: Software Development
Classifier: Topic :: System :: Clustering
Classifier: Topic :: System :: Distributed Computing
Classifier: Framework :: AsyncIO
Requires-Python: >=3.9
License-File: LICENSE
Requires-Dist: backend.ai-client (<22.4.0,~=22.3.0)
Provides-Extra: agent
Requires-Dist: backend.ai-agent (<22.4.0,>=22.3.0) ; extra == 'agent'
Provides-Extra: build
Requires-Dist: wheel (>=0.37.0) ; extra == 'build'
Requires-Dist: twine (>=3.5.0) ; extra == 'build'
Requires-Dist: setuptools (>=60.0.0) ; extra == 'build'
Provides-Extra: dev
Provides-Extra: docs
Requires-Dist: sphinx (~=3.3) ; extra == 'docs'
Requires-Dist: sphinx-rtd-theme (>=1.0.0) ; extra == 'docs'
Requires-Dist: pygments (~=2.6) ; extra == 'docs'
Provides-Extra: lint
Requires-Dist: flake8 (>=4.0.1) ; extra == 'lint'
Provides-Extra: manager
Requires-Dist: backend.ai-manager (<22.4.0,>=21.3.0) ; extra == 'manager'
Provides-Extra: test
Requires-Dist: pytest (>=6.2.5) ; extra == 'test'
Provides-Extra: typecheck
Requires-Dist: mypy (>=0.930) ; extra == 'typecheck'
